verifly/__init__.py
verifly/client.py
verifly/errors.py
verifly/resources/__init__.py
verifly/resources/verification.py
verifly/resources/webhook.py
verifly/utils/__init__.py
verifly/utils/request.py
verifly_sdk-1.0.0.dist-info/licenses/LICENSE
verifly_sdk-1.0.0.dist-info/METADATA
verifly_sdk-1.0.0.dist-info/WHEEL
verifly_sdk-1.0.0.dist-info/top_level.txt
verifly_sdk-1.0.0.dist-info/RECORD
