Metadata-Version: 2.4
Name: verifly-sdk
Version: 1.0.0
Summary: Official Python SDK for Verifly - Inbound 2FA Verification System with HMAC-SHA256 Authentication
Home-page: https://www.verifly.net
Author: SOCIFLY SOFTWARE LTD.
Author-email: info@verifly.net
License: MIT
Project-URL: Documentation, https://www.verifly.net/docs
Project-URL: Source, https://github.com/tlgsn/verifly-python-sdk
Project-URL: Bug Reports, https://github.com/tlgsn/verifly-python-sdk/issues
Keywords: verifly 2fa verification sms whatsapp email otp authentication
Classifier: Development Status :: 5 - Production/Stable
Classifier: Intended Audience :: Developers
Classifier: License :: OSI Approved :: MIT License
Classifier: Programming Language :: Python :: 3
Classifier: Programming Language :: Python :: 3.6
Classifier: Programming Language :: Python :: 3.7
Classifier: Programming Language :: Python :: 3.8
Classifier: Programming Language :: Python :: 3.9
Classifier: Programming Language :: Python :: 3.10
Classifier: Programming Language :: Python :: 3.11
Classifier: Topic :: Software Development :: Libraries :: Python Modules
Classifier: Topic :: Security
Classifier: Topic :: Communications
Requires-Python: >=3.6
License-File: LICENSE
Requires-Dist: requests>=2.25.0
Dynamic: author
Dynamic: author-email
Dynamic: classifier
Dynamic: description
Dynamic: description-content-type
Dynamic: home-page
Dynamic: keywords
Dynamic: license
Dynamic: license-file
Dynamic: project-url
Dynamic: requires-dist
Dynamic: requires-python
Dynamic: summary
